switchmateble_mreschenberg/__init__.py
switchmateble_mreschenberg/switchmateble.py
switchmateble_mreschenberg-0.0.1.dist-info/LICENSE
switchmateble_mreschenberg-0.0.1.dist-info/METADATA
switchmateble_mreschenberg-0.0.1.dist-info/WHEEL
switchmateble_mreschenberg-0.0.1.dist-info/top_level.txt
switchmateble_mreschenberg-0.0.1.dist-info/RECORD
