Metadata-Version: 2.1
Name: switchmateble-mreschenberg
Version: 0.0.1
Summary: A bluetooth based package for interacting with switchmates
Author-email: Morgan Reschenberg <shatterthestars@gmail.com>
License: MIT License        
Project-URL: Homepage, https://github.com/mreschenberg/switchmateble
Project-URL: Bug Tracker, https://github.com/mreschenberg/switchmateble/issues
Classifier: Programming Language :: Python :: 3
Classifier: License :: OSI Approved :: MIT License
Classifier: Operating System :: OS Independent
Requires-Python: >=3.7
License-File: LICENSE
